[
  {
    "2010": [
      {
        "wilayah": "Kabupaten",
        "name": "Pandeglang",
        "tingkat": "dua",
        "data": 11.23
      },
      {
        "wilayah": "Kabupaten",
        "name": "Lebak",
        "tingkat": "dua",
        "data": 10.35
      },
      {
        "wilayah": "Kabupaten",
        "name": "Tangerang",
        "tingkat": "dua",
        "data": 10.77
      },
      {
        "wilayah": "Kabupaten",
        "name": "Serang",
        "tingkat": "dua",
        "data": 10.74
      },
      {
        "wilayah": "Kota",
        "name": "Tangerang",
        "tingkat": "dua",
        "data": 11.56
      },
      {
        "wilayah": "Kota",
        "name": "Cilegon",
        "tingkat": "dua",
        "data": 11.56
      },
      {
        "wilayah": "Kota",
        "name": "Serang",
        "tingkat": "dua",
        "data": 10.98
      },
      {
        "wilayah": "Kota",
        "name": "Tangerang Selatan",
        "tingkat": "dua",
        "data": 12.08
      }
    ],
    "2011": [
      {
        "wilayah": "Kabupaten",
        "name": "Pandeglang",
        "tingkat": "dua",
        "data": 11.81
      },
      {
        "wilayah": "Kabupaten",
        "name": "Lebak",
        "tingkat": "dua",
        "data": 10.83
      },
      {
        "wilayah": "Kabupaten",
        "name": "Tangerang",
        "tingkat": "dua",
        "data": 10.99
      },
      {
        "wilayah": "Kabupaten",
        "name": "Serang",
        "tingkat": "dua",
        "data": 11.23
      },
      {
        "wilayah": "Kota",
        "name": "Tangerang",
        "tingkat": "dua",
        "data": 11.86
      },
      {
        "wilayah": "Kota",
        "name": "Cilegon",
        "tingkat": "dua",
        "data": 11.88
      },
      {
        "wilayah": "Kota",
        "name": "Serang",
        "tingkat": "dua",
        "data": 11.27
      },
      {
        "wilayah": "Kota",
        "name": "Tangerang Selatan",
        "tingkat": "dua",
        "data": 12.43
      }
    ],
    "2012": [
      {
        "wilayah": "Kabupaten",
        "name": "Pandeglang",
        "tingkat": "dua",
        "data": 12.17
      },
      {
        "wilayah": "Kabupaten",
        "name": "Lebak",
        "tingkat": "dua",
        "data": 10.96
      },
      {
        "wilayah": "Kabupaten",
        "name": "Tangerang",
        "tingkat": "dua",
        "data": 11.18
      },
      {
        "wilayah": "Kabupaten",
        "name": "Serang",
        "tingkat": "dua",
        "data": 11.72
      },
      {
        "wilayah": "Kota",
        "name": "Tangerang",
        "tingkat": "dua",
        "data": 12.23
      },
      {
        "wilayah": "Kota",
        "name": "Cilegon",
        "tingkat": "dua",
        "data": 12.18
      },
      {
        "wilayah": "Kota",
        "name": "Serang",
        "tingkat": "dua",
        "data": 11.82
      },
      {
        "wilayah": "Kota",
        "name": "Tangerang Selatan",
        "tingkat": "dua",
        "data": 12.79
      }
    ],
    "2013": [
      {
        "wilayah": "Kabupaten",
        "name": "Pandeglang",
        "tingkat": "dua",
        "data": 12.86
      },
      {
        "wilayah": "Kabupaten",
        "name": "Lebak",
        "tingkat": "dua",
        "data": 11.55
      },
      {
        "wilayah": "Kabupaten",
        "name": "Tangerang",
        "tingkat": "dua",
        "data": 11.44
      },
      {
        "wilayah": "Kabupaten",
        "name": "Serang",
        "tingkat": "dua",
        "data": 12.09
      },
      {
        "wilayah": "Kota",
        "name": "Tangerang",
        "tingkat": "dua",
        "data": 12.60
      },
      {
        "wilayah": "Kota",
        "name": "Cilegon",
        "tingkat": "dua",
        "data": 12.67
      },
      {
        "wilayah": "Kota",
        "name": "Serang",
        "tingkat": "dua",
        "data": 11.92
      },
      {
        "wilayah": "Kota",
        "name": "Tangerang Selatan",
        "tingkat": "dua",
        "data": 13.24
      }
    ],
    "2014": [
      {
        "wilayah": "Kabupaten",
        "name": "Pandeglang",
        "tingkat": "dua",
        "data": 13.38
      },
      {
        "wilayah": "Kabupaten",
        "name": "Lebak",
        "tingkat": "dua",
        "data": 11.88
      },
      {
        "wilayah": "Kabupaten",
        "name": "Tangerang",
        "tingkat": "dua",
        "data": 11.65
      },
      {
        "wilayah": "Kabupaten",
        "name": "Serang",
        "tingkat": "dua",
        "data": 12.35
      },
      {
        "wilayah": "Kota",
        "name": "Tangerang",
        "tingkat": "dua",
        "data": 12.86
      },
      {
        "wilayah": "Kota",
        "name": "Cilegon",
        "tingkat": "dua",
        "data": 13.07
      },
      {
        "wilayah": "Kota",
        "name": "Serang",
        "tingkat": "dua",
        "data": 12.34
      },
      {
        "wilayah": "Kota",
        "name": "Tangerang Selatan",
        "tingkat": "dua",
        "data": 13.58
      }
    ],
    "2015": [
      {
        "wilayah": "Kabupaten",
        "name": "Pandeglang",
        "tingkat": "dua",
        "data": 13.39
      },
      {
        "wilayah": "Kabupaten",
        "name": "Lebak",
        "tingkat": "dua",
        "data": 11.90
      },
      {
        "wilayah": "Kabupaten",
        "name": "Tangerang",
        "tingkat": "dua",
        "data": 11.89
      },
      {
        "wilayah": "Kabupaten",
        "name": "Serang",
        "tingkat": "dua",
        "data": 12.36
      },
      {
        "wilayah": "Kota",
        "name": "Tangerang",
        "tingkat": "dua",
        "data": 12.90
      },
      {
        "wilayah": "Kota",
        "name": "Cilegon",
        "tingkat": "dua",
        "data": 13.10
      },
      {
        "wilayah": "Kota",
        "name": "Serang",
        "tingkat": "dua",
        "data": 12.36
      },
      {
        "wilayah": "Kota",
        "name": "Tangerang Selatan",
        "tingkat": "dua",
        "data": 13.61
      }
    ]
  }
]
